{
  "album_type": "album",
  "artists": [{
    "external_urls": {
      "spotify": "https://open.spotify.com/artist/51Blml2LZPmy7TTiAg47vQ"
    },
    "href": "https://api.spotify.com/v1/artists/51Blml2LZPmy7TTiAg47vQ",
    "id": "51Blml2LZPmy7TTiAg47vQ",
    "name": "U2",
    "type": "artist",
    "uri": "spotify:artist:51Blml2LZPmy7TTiAg47vQ"
  }],
  "available_markets": ["AD", "AE", "AG", "AL", "AM", "AO", "AR", "AT", "AU", "AZ", "BA", "BB", "BD", "BE", "BF", "BG", "BH", "BI", "BJ", "BN", "BO", "BR", "BS", "BT", "BW", "BY", "BZ", "CA", "CH", "CI", "CL", "CM", "CO", "CR", "CV", "CW", "CY", "CZ", "DE", "DJ", "DK", "DM", "DO", "DZ", "EC", "EE", "EG", "ES", "FI", "FJ", "FM", "FR", "GA", "GB", "GD", "GE", "GH", "GM", "GN", "GQ", "GR", "GT", "GW", "GY", "HK", "HN", "HR", "HT", "HU", "ID", "IE", "IL", "IN", "IS", "IT", "JM", "JO", "JP", "KE", "KG", "KH", "KI", "KM", "KN", "KR", "KW", "KZ", "LA", "LB", "LC", "LI", "LK", "LR", "LS", "LT", "LU", "LV", "MA", "MC", "MD", "ME", "MG", "MH", "MK", "ML", "MN", "MO", "MR", "MT", "MU", "MV", "MW", "MX", "MY", "MZ", "NA", "NE", "NG", "NI", "NL", "NO", "NP", "NR", "NZ", "OM", "PA", "PE", "PG", "PH", "PK", "PL", "PS", "PT", "PW", "PY", "QA", "RO", "RS", "RU", "RW", "SA", "SB", "SC", "SE", "SG", "SI", "SK", "SL", "SM", "SN", "SR", "ST", "SV", "SZ", "TD", "TG", "TH", "TL", "TN", "TO", "TR", "TT", "TV", "TW", "TZ", "UA", "UG", "US", "UY", "UZ", "VC", "VN", "VU", "WS", "XK", "ZA", "ZM", "ZW"],
  "copyrights": [{
    "text": "© 2007 Universal-Island Records Ltd., under exclusive licence to Mercury Records Limited",
    "type": "C"
  }, {
    "text": "℗ 2007 Universal-Island Records Ltd., under exclusive licence to Mercury Records Limited",
    "type": "P"
  }],
  "external_ids": {
    "upc": "00602517449398"
  },
  "external_urls": {
    "spotify": "https://open.spotify.com/album/5vBZRYu2GLA65nfxBvG1a7"
  },
  "genres": [],
  "href": "https://api.spotify.com/v1/albums/5vBZRYu2GLA65nfxBvG1a7",
  "id": "5vBZRYu2GLA65nfxBvG1a7",
  "images": [{
    "height": 640,
    "url": "https://i.scdn.co/image/ab67616d0000b273f8996a3f97e80d9d700635c3",
    "width": 640
  }, {
    "height": 300,
    "url": "https://i.scdn.co/image/ab67616d00001e02f8996a3f97e80d9d700635c3",
    "width": 300
  }, {
    "height": 64,
    "url": "https://i.scdn.co/image/ab67616d00004851f8996a3f97e80d9d700635c3",
    "width": 64
  }],
  "label": "Universal-Island Records Ltd.",
  "name": "The Joshua Tree",
  "popularity": 58,
  "release_date": "1987-03-10",
  "release_date_precision": "day",
  "total_tracks": 11,
  "tracks": {
    "href": "https://api.spotify.com/v1/albums/5vBZRYu2GLA65nfxBvG1a7/tracks?offset=0&limit=50",
    "items": [{
      "artists": [{
        "external_urls": {
          "spotify": "https://open.spotify.com/artist/51Blml2LZPmy7TTiAg47vQ"
        },
        "href": "https://api.spotify.com/v1/artists/51Blml2LZPmy7TTiAg47vQ",
        "id": "51Blml2LZPmy7TTiAg47vQ",
        "name": "U2",
        "type": "artist",
        "uri": "spotify:artist:51Blml2LZPmy7TTiAg47vQ"
      }],
      "available_markets": ["AD", "AE", "AG", "AL", "AM", "AO", "AR", "AT", "AU", "AZ", "BA", "BB", "BD", "BE", "BF", "BG", "BH", "BI", "BJ", "BN", "BO", "BR", "BS", "BT", "BW", "BY", "BZ", "CA", "CH", "CI", "CL", "CM", "CO", "CR", "CV", "CW", "CY", "CZ", "DE", "DJ", "DK", "DM", "DO", "DZ", "EC", "EE", "EG", "ES", "FI", "FJ", "FM", "FR", "GA", "GB", "GD", "GE", "GH", "GM", "GN", "GQ", "GR", "GT", "GW", "GY", "HK", "HN", "HR", "HT", "HU", "ID", "IE", "IL", "IN", "IS", "IT", "JM", "JO", "JP", "KE", "KG", "KH", "KI", "KM", "KN", "KR", "KW", "KZ", "LA", "LB", "LC", "LI", "LK", "LR", "LS", "LT", "LU", "LV", "MA", "MC", "MD", "ME", "MG", "MH", "MK", "ML", "MN", "MO", "MR", "MT", "MU", "MV", "MW", "MX", "MY", "MZ", "NA", "NE", "NG", "NI", "NL", "NO", "NP", "NR", "NZ", "OM", "PA", "PE", "PG", "PH", "PK", "PL", "PS", "PT", "PW", "PY", "QA", "RO", "RS", "RU", "RW", "SA", "SB", "SC", "SE", "SG", "SI", "SK", "SL", "SM", "SN", "SR", "ST", "SV", "SZ", "TD", "TG", "TH", "TL", "TN", "TO", "TR", "TT", "TV", "TW", "TZ", "UA", "UG", "US", "UY", "UZ", "VC", "VN", "VU", "WS", "XK", "ZA", "ZM", "ZW"],
      "disc_number": 1,
      "duration_ms": 336613,
      "explicit": false,
      "external_urls": {
        "spotify": "https://open.spotify.com/track/7h1YqA5MZrRxmkUFpukRcp"
      },
      "href": "https://api.spotify.com/v1/tracks/7h1YqA5MZrRxmkUFpukRcp",
      "id": "7h1YqA5MZrRxmkUFpukRcp",
      "is_local": false,
      "name": "Where The Streets Have No Name - Remastered",
      "preview_url": null,
      "track_number": 1,
      "type": "track",
      "uri": "spotify:track:7h1YqA5MZrRxmkUFpukRcp"
    }, {
      "artists": [{
        "external_urls": {
          "spotify": "https://open.spotify.com/artist/51Blml2LZPmy7TTiAg47vQ"
        },
        "href": "https://api.spotify.com/v1/artists/51Blml2LZPmy7TTiAg47vQ",
        "id": "51Blml2LZPmy7TTiAg47vQ",
        "name": "U2",
        "type": "artist",
        "uri": "spotify:artist:51Blml2LZPmy7TTiAg47vQ"
      }],
      "available_markets": ["AD", "AE", "AG", "AL", "AM", "AO", "AR", "AT", "AU", "AZ", "BA", "BB", "BD", "BE", "BF", "BG", "BH", "BI", "BJ", "BN", "BO", "BR", "BS", "BT", "BW", "BY", "BZ", "CA", "CH", "CI", "CL", "CM", "CO", "CR", "CV", "CW", "CY", "CZ", "DE", "DJ", "DK", "DM", "DO", "DZ", "EC", "EE", "EG", "ES", "FI", "FJ", "FM", "FR", "GA", "GB", "GD", "GE", "GH", "GM", "GN", "GQ", "GR", "GT", "GW", "GY", "HK", "HN", "HR", "HT", "HU", "ID", "IE", "IL", "IN", "IS", "IT", "JM", "JO", "JP", "KE", "KG", "KH", "KI", "KM", "KN", "KR", "KW", "KZ", "LA", "LB", "LC", "LI", "LK", "LR", "LS", "LT", "LU", "LV", "MA", "MC", "MD", "ME", "MG", "MH", "MK", "ML", "MN", "MO", "MR", "MT", "MU", "MV", "MW", "MX", "MY", "MZ", "NA", "NE", "NG", "NI", "NL", "NO", "NP", "NR", "NZ", "OM", "PA", "PE", "PG", "PH", "PK", "PL", "PS", "PT", "PW", "PY", "QA", "RO", "RS", "RU", "RW", "SA", "SB", "SC", "SE", "SG", "SI", "SK", "SL", "SM", "SN", "SR", "ST", "SV", "SZ", "TD", "TG", "TH", "TL", "TN", "TO", "TR", "TT", "TV", "TW", "TZ", "UA", "UG", "US", "UY", "UZ", "VC", "VN", "VU", "WS", "XK", "ZA", "ZM", "ZW"],
      "disc_number": 1,
      "duration_ms": 277480,
      "explicit": false,
      "external_urls": {
        "spotify": "https://open.spotify.com/track/3MRQ3CSjoiV1HFil8ykM9M"
      },
      "href": "https://api.spotify.com/v1/tracks/3MRQ3CSjoiV1HFil8ykM9M",
      "id": "3MRQ3CSjoiV1HFil8ykM9M",
      "is_local": false,
      "name": "I Still Haven't Found What I'm Looking For - Remastered 2007",
      "preview_url": null,
      "track_number": 2,
      "type": "track",
      "uri": "spotify:track:3MRQ3CSjoiV1HFil8ykM9M"
    }, {
      "artists": [{
        "external_urls": {
          "spotify": "https://open.spotify.com/artist/51Blml2LZPmy7TTiAg47vQ"
        },
        "href": "https://api.spotify.com/v1/artists/51Blml2LZPmy7TTiAg47vQ",
        "id": "51Blml2LZPmy7TTiAg47vQ",
        "name": "U2",
        "type": "artist",
        "uri": "spotify:artist:51Blml2LZPmy7TTiAg47vQ"
      }],
      "available_markets": ["AD", "AE", "AG", "AL", "AM", "AO", "AR", "AT", "AU", "AZ", "BA", "BB", "BD", "BE", "BF", "BG", "BH", "BI", "BJ", "BN", "BO", "BR", "BS", "BT", "BW", "BY", "BZ", "CA", "CH", "CI", "CL", "CM", "CO", "CR", "CV", "CW", "CY", "CZ", "DE", "DJ", "DK", "DM", "DO", "DZ", "EC", "EE", "EG", "ES", "FI", "FJ", "FM", "FR", "GA", "GB", "GD", "GE", "GH", "GM", "GN", "GQ", "GR", "GT", "GW", "GY", "HK", "HN", "HR", "HT", "HU", "ID", "IE", "IL", "IN", "IS", "IT", "JM", "JO", "JP", "KE", "KG", "KH", "KI", "KM", "KN", "KR", "KW", "KZ", "LA", "LB", "LC", "LI", "LK", "LR", "LS", "LT", "LU", "LV", "MA", "MC", "MD", "ME", "MG", "MH", "MK", "ML", "MN", "MO", "MR", "MT", "MU", "MV", "MW", "MX", "MY", "MZ", "NA", "NE", "NG", "NI", "NL", "NO", "NP", "NR", "NZ", "OM", "PA", "PE", "PG", "PH", "PK", "PL", "PS", "PT", "PW", "PY", "QA", "RO", "RS", "RU", "RW", "SA", "SB", "SC", "SE", "SG", "SI", "SK", "SL", "SM", "SN", "SR", "ST", "SV", "SZ", "TD", "TG", "TH", "TL", "TN", "TO", "TR", "TT", "TV", "TW", "TZ", "UA", "UG", "US", "UY", "UZ", "VC", "VN", "VU", "WS", "XK", "ZA", "ZM", "ZW"],
      "disc_number": 1,
      "duration_ms": 295520,
      "explicit": false,
      "external_urls": {
        "spotify": "https://open.spotify.com/track/2x45xqISlmmDJqxOqr8BuS"
      },
      "href": "https://api.spotify.com/v1/tracks/2x45xqISlmmDJqxOqr8BuS",
      "id": "2x45xqISlmmDJqxOqr8BuS",
      "is_local": false,
      "name": "With Or Without You - Remastered",
      "preview_url": null,
      "track_number": 3,
      "type": "track",
      "uri": "spotify:track:2x45xqISlmmDJqxOqr8BuS"
    }, {
      "artists": [{
        "external_urls": {
          "spotify": "https://open.spotify.com/artist/51Blml2LZPmy7TTiAg47vQ"
        },
        "href": "https://api.spotify.com/v1/artists/51Blml2LZPmy7TTiAg47vQ",
        "id": "51Blml2LZPmy7TTiAg47vQ",
        "name": "U2",
        "type": "artist",
        "uri": "spotify:artist:51Blml2LZPmy7TTiAg47vQ"
      }],
      "available_markets": ["AD", "AE", "AG", "AL", "AM", "AO", "AR", "AT", "AU", "AZ", "BA", "BB", "BD", "BE", "BF", "BG", "BH", "BI", "BJ", "BN", "BO", "BR", "BS", "BT", "BW", "BY", "BZ", "CA", "CH", "CI", "CL", "CM", "CO", "CR", "CV", "CW", "CY", "CZ", "DE", "DJ", "DK", "DM", "DO", "DZ", "EC", "EE", "EG", "ES", "FI", "FJ", "FM", "FR", "GA", "GB", "GD", "GE", "GH", "GM", "GN", "GQ", "GR", "GT", "GW", "GY", "HK", "HN", "HR", "HT", "HU", "ID", "IE", "IL", "IN", "IS", "IT", "JM", "JO", "JP", "KE", "KG", "KH", "KI", "KM", "KN", "KR", "KW", "KZ", "LA", "LB", "LC", "LI", "LK", "LR", "LS", "LT", "LU", "LV", "MA", "MC", "MD", "ME", "MG", "MH", "MK", "ML", "MN", "MO", "MR", "MT", "MU", "MV", "MW", "MX", "MY", "MZ", "NA", "NE", "NG", "NI", "NL", "NO", "NP", "NR", "NZ", "OM", "PA", "PE", "PG", "PH", "PK", "PL", "PS", "PT", "PW", "PY", "QA", "RO", "RS", "RU", "RW", "SA", "SB", "SC", "SE", "SG", "SI", "SK", "SL", "SM", "SN", "SR", "ST", "SV", "SZ", "TD", "TG", "TH", "TL", "TN", "TO", "TR", "TT", "TV", "TW", "TZ", "UA", "UG", "US", "UY", "UZ", "VC", "VN", "VU", "WS", "XK", "ZA", "ZM", "ZW"],
      "disc_number": 1,
      "duration_ms": 271546,
      "explicit": false,
      "external_urls": {
        "spotify": "https://open.spotify.com/track/1C6Tmo58WMtnAPdxYz9qCz"
      },
      "href": "https://api.spotify.com/v1/tracks/1C6Tmo58WMtnAPdxYz9qCz",
      "id": "1C6Tmo58WMtnAPdxYz9qCz",
      "is_local": false,
      "name": "Bullet The Blue Sky - Remastered 2007",
      "preview_url": null,
      "track_number": 4,
      "type": "track",
      "uri": "spotify:track:1C6Tmo58WMtnAPdxYz9qCz"
    }, {
      "artists": [{
        "external_urls": {
          "spotify": "https://open.spotify.com/artist/51Blml2LZPmy7TTiAg47vQ"
        },
        "href": "https://api.spotify.com/v1/artists/51Blml2LZPmy7TTiAg47vQ",
        "id": "51Blml2LZPmy7TTiAg47vQ",
        "name": "U2",
        "type": "artist",
        "uri": "spotify:artist:51Blml2LZPmy7TTiAg47vQ"
      }],
      "available_markets": ["AD", "AE", "AG", "AL", "AM", "AO", "AR", "AT", "AU", "AZ", "BA", "BB", "BD", "BE", "BF", "BG", "BH", "BI", "BJ", "BN", "BO", "BR", "BS", "BT", "BW", "BY", "BZ", "CA", "CH", "CI", "CL", "CM", "CO", "CR", "CV", "CW", "CY", "CZ", "DE", "DJ", "DK", "DM", "DO", "DZ", "EC", "EE", "EG", "ES", "FI", "FJ", "FM", "FR", "GA", "GB", "GD", "GE", "GH", "GM", "GN", "GQ", "GR", "GT", "GW", "GY", "HK", "HN", "HR", "HT", "HU", "ID", "IE", "IL", "IN", "IS", "IT", "JM", "JO", "JP", "KE", "KG", "KH", "KI", "KM", "KN", "KR", "KW", "KZ", "LA", "LB", "LC", "LI", "LK", "LR", "LS", "LT", "LU", "LV", "MA", "MC", "MD", "ME", "MG", "MH", "MK", "ML", "MN", "MO", "MR", "MT", "MU", "MV", "MW", "MX", "MY", "MZ", "NA", "NE", "NG", "NI", "NL", "NO", "NP", "NR", "NZ", "OM", "PA", "PE", "PG", "PH", "PK", "PL", "PS", "PT", "PW", "PY", "QA", "RO", "RS", "RU", "RW", "SA", "SB", "SC", "SE", "SG", "SI", "SK", "SL", "SM", "SN", "SR", "ST", "SV", "SZ", "TD", "TG", "TH", "TL", "TN", "TO", "TR", "TT", "TV", "TW", "TZ", "UA", "UG", "US", "UY", "UZ", "VC", "VN", "VU", "WS", "XK", "ZA", "ZM", "ZW"],
      "disc_number": 1,
      "duration_ms": 257186,
      "explicit": false,
      "external_urls": {
        "spotify": "https://open.spotify.com/track/741AUHHkjuWe9wSNIhmApn"
      },
      "href": "https://api.spotify.com/v1/tracks/741AUHHkjuWe9wSNIhmApn",
      "id": "741AUHHkjuWe9wSNIhmApn",
      "is_local": false,
      "name": "Running To Stand Still - Remastered 2007",
      "preview_url": null,
      "track_number": 5,
      "type": "track",
      "uri": "spotify:track:741AUHHkjuWe9wSNIhmApn"
    }, {
      "artists": [{
        "external_urls": {
          "spotify": "https://open.spotify.com/artist/51Blml2LZPmy7TTiAg47vQ"
        },
        "href": "https://api.spotify.com/v1/artists/51Blml2LZPmy7TTiAg47vQ",
        "id": "51Blml2LZPmy7TTiAg47vQ",
        "name": "U2",
        "type": "artist",
        "uri": "spotify:artist:51Blml2LZPmy7TTiAg47vQ"
      }],
      "available_markets": ["AD", "AE", "AG", "AL", "AM", "AO", "AR", "AT", "AU", "AZ", "BA", "BB", "BD", "BE", "BF", "BG", "BH", "BI", "BJ", "BN", "BO", "BR", "BS", "BT", "BW", "BY", "BZ", "CA", "CH", "CI", "CL", "CM", "CO", "CR", "CV", "CW", "CY", "CZ", "DE", "DJ", "DK", "DM", "DO", "DZ", "EC", "EE", "EG", "ES", "FI", "FJ", "FM", "FR", "GA", "GB", "GD", "GE", "GH", "GM", "GN", "GQ", "GR", "GT", "GW", "GY", "HK", "HN", "HR", "HT", "HU", "ID", "IE", "IL", "IN", "IS", "IT", "JM", "JO", "JP", "KE", "KG", "KH", "KI", "KM", "KN", "KR", "KW", "KZ", "LA", "LB", "LC", "LI", "LK", "LR", "LS", "LT", "LU", "LV", "MA", "MC", "MD", "ME", "MG", "MH", "MK", "ML", "MN", "MO", "MR", "MT", "MU", "MV", "MW", "MX", "MY", "MZ", "NA", "NE", "NG", "NI", "NL", "NO", "NP", "NR", "NZ", "OM", "PA", "PE", "PG", "PH", "PK", "PL", "PS", "PT", "PW", "PY", "QA", "RO", "RS", "RU", "RW", "SA", "SB", "SC", "SE", "SG", "SI", "SK", "SL", "SM", "SN", "SR", "ST", "SV", "SZ", "TD", "TG", "TH", "TL", "TN", "TO", "TR", "TT", "TV", "TW", "TZ", "UA", "UG", "US", "UY", "UZ", "VC", "VN", "VU", "WS", "XK", "ZA", "ZM", "ZW"],
      "disc_number": 1,
      "duration_ms": 292866,
      "explicit": false,
      "external_urls": {
        "spotify": "https://open.spotify.com/track/4gE5Z3sOcWYyR0SezjvAj5"
      },
      "href": "https://api.spotify.com/v1/tracks/4gE5Z3sOcWYyR0SezjvAj5",
      "id": "4gE5Z3sOcWYyR0SezjvAj5",
      "is_local": false,
      "name": "Red Hill Mining Town - Remastered 2007",
      "preview_url": null,
      "track_number": 6,
      "type": "track",
      "uri": "spotify:track:4gE5Z3sOcWYyR0SezjvAj5"
    }, {
      "artists": [{
        "external_urls": {
          "spotify": "https://open.spotify.com/artist/51Blml2LZPmy7TTiAg47vQ"
        },
        "href": "https://api.spotify.com/v1/artists/51Blml2LZPmy7TTiAg47vQ",
        "id": "51Blml2LZPmy7TTiAg47vQ",
        "name": "U2",
        "type": "artist",
        "uri": "spotify:artist:51Blml2LZPmy7TTiAg47vQ"
      }],
      "available_markets": ["AD", "AE", "AG", "AL", "AM", "AO", "AR", "AT", "AU", "AZ", "BA", "BB", "BD", "BE", "BF", "BG", "BH", "BI", "BJ", "BN", "BO", "BR", "BS", "BT", "BW", "BY", "BZ", "CA", "CH", "CI", "CL", "CM", "CO", "CR", "CV", "CW", "CY", "CZ", "DE", "DJ", "DK", "DM", "DO", "DZ", "EC", "EE", "EG", "ES", "FI", "FJ", "FM", "FR", "GA", "GB", "GD", "GE", "GH", "GM", "GN", "GQ", "GR", "GT", "GW", "GY", "HK", "HN", "HR", "HT", "HU", "ID", "IE", "IL", "IN", "IS", "IT", "JM", "JO", "JP", "KE", "KG", "KH", "KI", "KM", "KN", "KR", "KW", "KZ", "LA", "LB", "LC", "LI", "LK", "LR", "LS", "LT", "LU", "LV", "MA", "MC", "MD", "ME", "MG", "MH", "MK", "ML", "MN", "MO", "MR", "MT", "MU", "MV", "MW", "MX", "MY", "MZ", "NA", "NE", "NG", "NI", "NL", "NO", "NP", "NR", "NZ", "OM", "PA", "PE", "PG", "PH", "PK", "PL", "PS", "PT", "PW", "PY", "QA", "RO", "RS", "RU", "RW", "SA", "SB", "SC", "SE", "SG", "SI", "SK", "SL", "SM", "SN", "SR", "ST", "SV", "SZ", "TD", "TG", "TH", "TL", "TN", "TO", "TR", "TT", "TV", "TW", "TZ", "UA", "UG", "US", "UY", "UZ", "VC", "VN", "VU", "WS", "XK", "ZA", "ZM", "ZW"],
      "disc_number": 1,
      "duration_ms": 176600,
      "explicit": false,
      "external_urls": {
        "spotify": "https://open.spotify.com/track/1jNWu1c5ilLHUHT0DhLOQB"
      },
      "href": "https://api.spotify.com/v1/tracks/1jNWu1c5ilLHUHT0DhLOQB",
      "id": "1jNWu1c5ilLHUHT0DhLOQB",
      "is_local": false,
      "name": "In God's Country - Remastered 2007",
      "preview_url": null,
      "track_number": 7,
      "type": "track",
      "uri": "spotify:track:1jNWu1c5ilLHUHT0DhLOQB"
    }, {
      "artists": [{
        "external_urls": {
          "spotify": "https://open.spotify.com/artist/51Blml2LZPmy7TTiAg47vQ"
        },
        "href": "https://api.spotify.com/v1/artists/51Blml2LZPmy7TTiAg47vQ",
        "id": "51Blml2LZPmy7TTiAg47vQ",
        "name": "U2",
        "type": "artist",
        "uri": "spotify:artist:51Blml2LZPmy7TTiAg47vQ"
      }],
      "available_markets": ["AD", "AE", "AG", "AL", "AM", "AO", "AR", "AT", "AU", "AZ", "BA", "BB", "BD", "BE", "BF", "BG", "BH", "BI", "BJ", "BN", "BO", "BR", "BS", "BT", "BW", "BY", "BZ", "CA", "CH", "CI", "CL", "CM", "CO", "CR", "CV", "CW", "CY", "CZ", "DE", "DJ", "DK", "DM", "DO", "DZ", "EC", "EE", "EG", "ES", "FI", "FJ", "FM", "FR", "GA", "GB", "GD", "GE", "GH", "GM", "GN", "GQ", "GR", "GT", "GW", "GY", "HK", "HN", "HR", "HT", "HU", "ID", "IE", "IL", "IN", "IS", "IT", "JM", "JO", "JP", "KE", "KG", "KH", "KI", "KM", "KN", "KR", "KW", "KZ", "LA", "LB", "LC", "LI", "LK", "LR", "LS", "LT", "LU", "LV", "MA", "MC", "MD", "ME", "MG", "MH", "MK", "ML", "MN", "MO", "MR", "MT", "MU", "MV", "MW", "MX", "MY", "MZ", "NA", "NE", "NG", "NI", "NL", "NO", "NP", "NR", "NZ", "OM", "PA", "PE", "PG", "PH", "PK", "PL", "PS", "PT", "PW", "PY", "QA", "RO", "RS", "RU", "RW", "SA", "SB", "SC", "SE", "SG", "SI", "SK", "SL", "SM", "SN", "SR", "ST", "SV", "SZ", "TD", "TG", "TH", "TL", "TN", "TO", "TR", "TT", "TV", "TW", "TZ", "UA", "UG", "US", "UY", "UZ", "VC", "VN", "VU", "WS", "XK", "ZA", "ZM", "ZW"],
      "disc_number": 1,
      "duration_ms": 211813,
      "explicit": false,
      "external_urls": {
        "spotify": "https://open.spotify.com/track/6w9BH6tSPMgl6KRz1YuONG"
      },
      "href": "https://api.spotify.com/v1/tracks/6w9BH6tSPMgl6KRz1YuONG",
      "id": "6w9BH6tSPMgl6KRz1YuONG",
      "is_local": false,
      "name": "Trip Through Your Wires - Remastered 2007",
      "preview_url": null,
      "track_number": 8,
      "type": "track",
      "uri": "spotify:track:6w9BH6tSPMgl6KRz1YuONG"
    }, {
      "artists": [{
        "external_urls": {
          "spotify": "https://open.spotify.com/artist/51Blml2LZPmy7TTiAg47vQ"
        },
        "href": "https://api.spotify.com/v1/artists/51Blml2LZPmy7TTiAg47vQ",
        "id": "51Blml2LZPmy7TTiAg47vQ",
        "name": "U2",
        "type": "artist",
        "uri": "spotify:artist:51Blml2LZPmy7TTiAg47vQ"
      }],
      "available_markets": ["AD", "AE", "AG", "AL", "AM", "AO", "AR", "AT", "AU", "AZ", "BA", "BB", "BD", "BE", "BF", "BG", "BH", "BI", "BJ", "BN", "BO", "BR", "BS", "BT", "BW", "BY", "BZ", "CA", "CH", "CI", "CL", "CM", "CO", "CR", "CV", "CW", "CY", "CZ", "DE", "DJ", "DK", "DM", "DO", "DZ", "EC", "EE", "EG", "ES", "FI", "FJ", "FM", "FR", "GA", "GB", "GD", "GE", "GH", "GM", "GN", "GQ", "GR", "GT", "GW", "GY", "HK", "HN", "HR", "HT", "HU", "ID", "IE", "IL", "IN", "IS", "IT", "JM", "JO", "JP", "KE", "KG", "KH", "KI", "KM", "KN", "KR", "KW", "KZ", "LA", "LB", "LC", "LI", "LK", "LR", "LS", "LT", "LU", "LV", "MA", "MC", "MD", "ME", "MG", "MH", "MK", "ML", "MN", "MO", "MR", "MT", "MU", "MV", "MW", "MX", "MY", "MZ", "NA", "NE", "NG", "NI", "NL", "NO", "NP", "NR", "NZ", "OM", "PA", "PE", "PG", "PH", "PK", "PL", "PS", "PT", "PW", "PY", "QA", "RO", "RS", "RU", "RW", "SA", "SB", "SC", "SE", "SG", "SI", "SK", "SL", "SM", "SN", "SR", "ST", "SV", "SZ", "TD", "TG", "TH", "TL", "TN", "TO", "TR", "TT", "TV", "TW", "TZ", "UA", "UG", "US", "UY", "UZ", "VC", "VN", "VU", "WS", "XK", "ZA", "ZM", "ZW"],
      "disc_number": 1,
      "duration_ms": 322373,
      "explicit": false,
      "external_urls": {
        "spotify": "https://open.spotify.com/track/7JFMf61pdg8H8NEMgxdHYx"
      },
      "href": "https://api.spotify.com/v1/tracks/7JFMf61pdg8H8NEMgxdHYx",
      "id": "7JFMf61pdg8H8NEMgxdHYx",
      "is_local": false,
      "name": "One Tree Hill - Remastered 2007",
      "preview_url": null,
      "track_number": 9,
      "type": "track",
      "uri": "spotify:track:7JFMf61pdg8H8NEMgxdHYx"
    }, {
      "artists": [{
        "external_urls": {
          "spotify": "https://open.spotify.com/artist/51Blml2LZPmy7TTiAg47vQ"
        },
        "href": "https://api.spotify.com/v1/artists/51Blml2LZPmy7TTiAg47vQ",
        "id": "51Blml2LZPmy7TTiAg47vQ",
        "name": "U2",
        "type": "artist",
        "uri": "spotify:artist:51Blml2LZPmy7TTiAg47vQ"
      }],
      "available_markets": ["AD", "AE", "AG", "AL", "AM", "AO", "AR", "AT", "AU", "AZ", "BA", "BB", "BD", "BE", "BF", "BG", "BH", "BI", "BJ", "BN", "BO", "BR", "BS", "BT", "BW", "BY", "BZ", "CA", "CH", "CI", "CL", "CM", "CO", "CR", "CV", "CW", "CY", "CZ", "DE", "DJ", "DK", "DM", "DO", "DZ", "EC", "EE", "EG", "ES", "FI", "FJ", "FM", "FR", "GA", "GB", "GD", "GE", "GH", "GM", "GN", "GQ", "GR", "GT", "GW", "GY", "HK", "HN", "HR", "HT", "HU", "ID", "IE", "IL", "IN", "IS", "IT", "JM", "JO", "JP", "KE", "KG", "KH", "KI", "KM", "KN", "KR", "KW", "KZ", "LA", "LB", "LC", "LI", "LK", "LR", "LS", "LT", "LU", "LV", "MA", "MC", "MD", "ME", "MG", "MH", "MK", "ML", "MN", "MO", "MR", "MT", "MU", "MV", "MW", "MX", "MY", "MZ", "NA", "NE", "NG", "NI", "NL", "NO", "NP", "NR", "NZ", "OM", "PA", "PE", "PG", "PH", "PK", "PL", "PS", "PT", "PW", "PY", "QA", "RO", "RS", "RU", "RW", "SA", "SB", "SC", "SE", "SG", "SI", "SK", "SL", "SM", "SN", "SR", "ST", "SV", "SZ", "TD", "TG", "TH", "TL", "TN", "TO", "TR", "TT", "TV", "TW", "TZ", "UA", "UG", "US", "UY", "UZ", "VC", "VN", "VU", "WS", "XK", "ZA", "ZM", "ZW"],
      "disc_number": 1,
      "duration_ms": 253040,
      "explicit": false,
      "external_urls": {
        "spotify": "https://open.spotify.com/track/6YLmaHGMKaKHCeEa03XRbI"
      },
      "href": "https://api.spotify.com/v1/tracks/6YLmaHGMKaKHCeEa03XRbI",
      "id": "6YLmaHGMKaKHCeEa03XRbI",
      "is_local": false,
      "name": "Exit - Remastered 2007",
      "preview_url": null,
      "track_number": 10,
      "type": "track",
      "uri": "spotify:track:6YLmaHGMKaKHCeEa03XRbI"
    }, {
      "artists": [{
        "external_urls": {
          "spotify": "https://open.spotify.com/artist/51Blml2LZPmy7TTiAg47vQ"
        },
        "href": "https://api.spotify.com/v1/artists/51Blml2LZPmy7TTiAg47vQ",
        "id": "51Blml2LZPmy7TTiAg47vQ",
        "name": "U2",
        "type": "artist",
        "uri": "spotify:artist:51Blml2LZPmy7TTiAg47vQ"
      }],
      "available_markets": ["AD", "AE", "AG", "AL", "AM", "AO", "AR", "AT", "AU", "AZ", "BA", "BB", "BD", "BE", "BF", "BG", "BH", "BI", "BJ", "BN", "BO", "BR", "BS", "BT", "BW", "BY", "BZ", "CA", "CH", "CI", "CL", "CM", "CO", "CR", "CV", "CW", "CY", "CZ", "DE", "DJ", "DK", "DM", "DO", "DZ", "EC", "EE", "EG", "ES", "FI", "FJ", "FM", "FR", "GA", "GB", "GD", "GE", "GH", "GM", "GN", "GQ", "GR", "GT", "GW", "GY", "HK", "HN", "HR", "HT", "HU", "ID", "IE", "IL", "IN", "IS", "IT", "JM", "JO", "JP", "KE", "KG", "KH", "KI", "KM", "KN", "KR", "KW", "KZ", "LA", "LB", "LC", "LI", "LK", "LR", "LS", "LT", "LU", "LV", "MA", "MC", "MD", "ME", "MG", "MH", "MK", "ML", "MN", "MO", "MR", "MT", "MU", "MV", "MW", "MX", "MY", "MZ", "NA", "NE", "NG", "NI", "NL", "NO", "NP", "NR", "NZ", "OM", "PA", "PE", "PG", "PH", "PK", "PL", "PS", "PT", "PW", "PY", "QA", "RO", "RS", "RU", "RW", "SA", "SB", "SC", "SE", "SG", "SI", "SK", "SL", "SM", "SN", "SR", "ST", "SV", "SZ", "TD", "TG", "TH", "TL", "TN", "TO", "TR", "TT", "TV", "TW", "TZ", "UA", "UG", "US", "UY", "UZ", "VC", "VN", "VU", "WS", "XK", "ZA", "ZM", "ZW"],
      "disc_number": 1,
      "duration_ms": 314226,
      "explicit": false,
      "external_urls": {
        "spotify": "https://open.spotify.com/track/7mzbAXvwMnQnc9uMgRJA4M"
      },
      "href": "https://api.spotify.com/v1/tracks/7mzbAXvwMnQnc9uMgRJA4M",
      "id": "7mzbAXvwMnQnc9uMgRJA4M",
      "is_local": false,
      "name": "Mothers Of The Disappeared - Remastered 2007",
      "preview_url": null,
      "track_number": 11,
      "type": "track",
      "uri": "spotify:track:7mzbAXvwMnQnc9uMgRJA4M"
    }],
    "limit": 50,
    "next": null,
    "offset": 0,
    "previous": null,
    "total": 11
  },
  "type": "album",
  "uri": "spotify:album:5vBZRYu2GLA65nfxBvG1a7"
}
